hlbox/__init__.py
hlbox/config.py
hlbox/exceptions.py
hlbox/sandboxes.py
hlbox/utils.py
hlbox-1.0.3.dist-info/DESCRIPTION.rst
hlbox-1.0.3.dist-info/METADATA
hlbox-1.0.3.dist-info/RECORD
hlbox-1.0.3.dist-info/WHEEL
hlbox-1.0.3.dist-info/metadata.json
hlbox-1.0.3.dist-info/pbr.json
hlbox-1.0.3.dist-info/top_level.txt
