Metadata-Version: 2.0
Name: hlbox
Version: 1.0.3
Summary: HLBox runs untrusted code in secure Docker based sandboxes (forked from [EpicBox](https://github.com/StepicOrg/epicbox))
Home-page: UNKNOWN
Author: Alex Gajewski
Author-email: agajews@gmail.com
License: UNKNOWN
Platform: UNKNOWN
Requires-Dist: docker (>=2)
Requires-Dist: python-dateutil (~=2.4)
Requires-Dist: requests (~=2.14)
Requires-Dist: structlog (>=15.3)
